lemma_agent/__init__.py
lemma_agent/adapters/__init__.py
lemma_agent/adapters/base.py
lemma_agent/adapters/langchain.py
lemma_agent/core/__init__.py
lemma_agent/core/collector.py
lemma_agent/core/config.py
lemma_agent/core/decorator.py
lemma_agent/core/tracer.py
lemma_agent/utils/__init__.py
lemma_agent/utils/logger.py
lemma_agent/utils/serialization.py
lemma_agent/utils/validation.py
lemma_agent-0.2.1.dist-info/METADATA
lemma_agent-0.2.1.dist-info/WHEEL
lemma_agent-0.2.1.dist-info/entry_points.txt
lemma_agent-0.2.1.dist-info/top_level.txt
lemma_agent-0.2.1.dist-info/RECORD
