Metadata-Version: 2.4
Name: lemma_agent
Version: 0.2.1
Summary: The GitHub Copilot for AI Agent Development - Intelligent debugging for AI agents
Home-page: https://github.com/fridayowl/Lemma
Author: Lemma Team
Author-email: Lemma Team <shinojcm01@gmail.com>
Maintainer-email: Lemma Team <shinojcm01@gmail.com>
License: MIT
Project-URL: Homepage, https://agentdebugger.pro
Project-URL: Documentation, https://docs.agentdebugger.pro
Project-URL: Repository, https://github.com/lemma-team/agentdebugger-pro
Project-URL: Issues, https://github.com/lemma-team/agentdebugger-pro/issues
Project-URL: Changelog, https://github.com/lemma-team/agentdebugger-pro/blob/main/CHANGELOG.md
Project-URL: Pitch Deck, https://agentdebugger.pro/pitch
Project-URL: Demo, https://agentdebugger.pro/demo
Keywords: ai,agents,debugging,llm,langchain,crewai,autogen,artificial-intelligence,machine-learning,development-tools,productivity,automation,chatbots,conversational-ai
Classifier: Development Status :: 4 - Beta
Classifier: Intended Audience :: Developers
Classifier: Intended Audience :: Science/Research
Classifier: Topic :: Software Development :: Debuggers
Classifier: Topic :: Software Development :: Libraries :: Python Modules
Classifier: Topic :: Scientific/Engineering :: Artificial Intelligence
Classifier: License :: OSI Approved :: MIT License
Classifier: Programming Language :: Python :: 3
Classifier: Programming Language :: Python :: 3.8
Classifier: Programming Language :: Python :: 3.9
Classifier: Programming Language :: Python :: 3.10
Classifier: Programming Language :: Python :: 3.11
Classifier: Programming Language :: Python :: 3.12
Classifier: Operating System :: OS Independent
Classifier: Framework :: AsyncIO
Requires-Python: >=3.8
Requires-Dist: typing-extensions>=4.0.0
Requires-Dist: dataclasses-json>=0.5.7
Requires-Dist: pydantic>=1.8.0
Requires-Dist: structlog>=21.1.0
Requires-Dist: msgpack>=1.0.0
Requires-Dist: httpx>=0.24.0
Requires-Dist: aiohttp>=3.8.0
Requires-Dist: pyyaml>=6.0
Requires-Dist: python-dotenv>=0.19.0
Requires-Dist: psutil>=5.8.0
Requires-Dist: tiktoken>=0.4.0
Provides-Extra: langchain
Requires-Dist: langchain>=0.1.0; extra == "langchain"
Requires-Dist: langchain-core>=0.1.0; extra == "langchain"
Provides-Extra: crewai
Requires-Dist: crewai>=0.1.0; extra == "crewai"
Provides-Extra: autogen
Requires-Dist: pyautogen>=0.1.0; extra == "autogen"
Provides-Extra: dev
Requires-Dist: pytest>=7.0.0; extra == "dev"
Requires-Dist: pytest-asyncio>=0.21.0; extra == "dev"
Requires-Dist: pytest-cov>=4.0.0; extra == "dev"
Requires-Dist: black>=22.0.0; extra == "dev"
Requires-Dist: isort>=5.10.0; extra == "dev"
Requires-Dist: flake8>=4.0.0; extra == "dev"
Requires-Dist: mypy>=0.991; extra == "dev"
Requires-Dist: pre-commit>=2.20.0; extra == "dev"
Provides-Extra: docs
Requires-Dist: sphinx>=4.5.0; extra == "docs"
Requires-Dist: sphinx-rtd-theme>=1.0.0; extra == "docs"
Requires-Dist: myst-parser>=0.17.0; extra == "docs"
Provides-Extra: all
Requires-Dist: langchain>=0.1.0; extra == "all"
Requires-Dist: langchain-core>=0.1.0; extra == "all"
Requires-Dist: crewai>=0.1.0; extra == "all"
Requires-Dist: pyautogen>=0.1.0; extra == "all"
Provides-Extra: enterprise
Requires-Dist: cryptography>=3.4.0; extra == "enterprise"
Requires-Dist: jwt>=1.3.0; extra == "enterprise"
Requires-Dist: redis>=4.0.0; extra == "enterprise"
Dynamic: author
Dynamic: home-page
Dynamic: requires-python
